jpeg_antecedent/__init__.py
jpeg_antecedent/block.py
jpeg_antecedent/build_incompatibility_likelihood.py
jpeg_antecedent/image.py
jpeg_antecedent/jpeg_toolbox.py
jpeg_antecedent/pipeline.py
jpeg_antecedent/run_on_dataset.py
jpeg_antecedent/utils.py
jpeg_antecedent-0.1.3.dist-info/LICENSE.md
jpeg_antecedent-0.1.3.dist-info/METADATA
jpeg_antecedent-0.1.3.dist-info/WHEEL
jpeg_antecedent-0.1.3.dist-info/top_level.txt
jpeg_antecedent-0.1.3.dist-info/RECORD
