Metadata-Version: 2.2
Name: jpeg-antecedent
Version: 0.1.3
Summary: Find possible antecedents of JPEG compression and decompression when the JPEG pipeline is known.
Home-page: https://github.com/EtienneLevecque/jpeg-antecedent
Author: Etienne Levecque
Author-email: pythonrepo.outbid878@silomails.com
Classifier: Programming Language :: Python :: 3
Classifier: License :: OSI Approved :: MIT License
Classifier: Operating System :: OS Independent
Requires-Python: >=3.12
License-File: LICENSE.md
Requires-Dist: numpy==2.2.0
Requires-Dist: pillow==11.0.0
Requires-Dist: scikit-image==0.25.0
Requires-Dist: jpeglib==1.0.1
Requires-Dist: scipy==1.14.1
Requires-Dist: gurobipy==11.0.3
Requires-Dist: PyYAML==6.0.2
Requires-Dist: rich==13.7.1
Requires-Dist: h5py~=3.10.0
Requires-Dist: pandas==2.2.3
Requires-Dist: setuptools==75.8.0
Dynamic: author
Dynamic: author-email
Dynamic: classifier
Dynamic: description
Dynamic: description-content-type
Dynamic: home-page
Dynamic: requires-dist
Dynamic: requires-python
Dynamic: summary
